mcp_monumenten/__init__.py
mcp_monumenten/__main__.py
mcp_monumenten/_dev.py
mcp_monumenten/server.py
mcp_monumenten-0.1.1.dist-info/licenses/LICENSE
mcp_monumenten-0.1.1.dist-info/METADATA
mcp_monumenten-0.1.1.dist-info/WHEEL
mcp_monumenten-0.1.1.dist-info/entry_points.txt
mcp_monumenten-0.1.1.dist-info/top_level.txt
mcp_monumenten-0.1.1.dist-info/RECORD
