Metadata-Version: 2.4
Name: mcp-monumenten
Version: 0.1.1
Summary: MCP server voor monumentale statussen in Nederland.
Author-email: Tomer Gabay <tomer.gabay@woonstadrotterdam.nl>, Ben Verhees <ben.verhees@woonstadrotterdam.nl>
License-Expression: MIT
Keywords: mcp,monumenten,rijksmonumenten,kadaster,gemeente
Classifier: Intended Audience :: Developers
Classifier: Programming Language :: Python :: 3
Classifier: Programming Language :: Python :: 3.10
Classifier: Programming Language :: Python :: 3.11
Classifier: Programming Language :: Python :: 3.12
Classifier: Programming Language :: Python :: 3.13
Requires-Python: >=3.10
License-File: LICENSE
Requires-Dist: dotenv>=0.9.9
Requires-Dist: mcp[cli]>=1.12.3
Requires-Dist: monumenten>=0.4.0
Dynamic: license-file
